setup.py
src/python_translate_cli/__init__.py
src/python_translate_cli/cli.py
src/python_translate_cli.egg-info/PKG-INFO
src/python_translate_cli.egg-info/SOURCES.txt
src/python_translate_cli.egg-info/dependency_links.txt
src/python_translate_cli.egg-info/entry_points.txt
src/python_translate_cli.egg-info/not-zip-safe
src/python_translate_cli.egg-info/requires.txt
src/python_translate_cli.egg-info/top_level.txt