Metadata-Version: 1.0
Name: python-translate-cli
Version: 0.0.1
Summary: 命令行查词
Home-page: http://sillymind.me
Author: mapleray
Author-email: zhiwuliao@gmail.com
License: GPL
Keywords: google,python,cli,dictionary,terminal
Platform: any
